MANIFEST.in
README.md
aio_downloader.json
setup.py
aio_downloader/__init__.py
aio_downloader/downloader.py
aio_downloader/engine.py
aio_downloader/sources.py
aio_downloader/utils.py
aio_downloader.egg-info/PKG-INFO
aio_downloader.egg-info/SOURCES.txt
aio_downloader.egg-info/dependency_links.txt
aio_downloader.egg-info/entry_points.txt
aio_downloader.egg-info/requires.txt
aio_downloader.egg-info/top_level.txt
aio_downloader.egg-info/zip-safe