Metadata-Version: 1.1
Name: aio-downloader
Version: 0.0.1
Summary: an async donwloader with muti-coroutine
Home-page: https://github.com/gudaolingshi/aio-downloader
Author: gudaolingshi
Author-email: shengleibu@163.com
License: MIT
Keywords: video downloader,async
Platform: UNKNOWN
Classifier: License :: OSI Approved :: MIT License
Classifier: Programming Language :: Python :: 3
Classifier: Intended Audience :: Developers
Classifier: Operating System :: OS Independent
